multitrackpy/__init__.py
multitrackpy/__main__.py
multitrackpy/helper.py
multitrackpy/image.py
multitrackpy/mtt.py
multitrackpy/mvd.py
multitrackpy/pointcloud.py
multitrackpy/rigid_body_transform_3d.py
multitrackpy/tracking.py
multitrackpy/tracking_opts.py
multitrackpy/triangulation.py
bbo_multitrackpy-1.2.0.dist-info/METADATA
bbo_multitrackpy-1.2.0.dist-info/WHEEL
bbo_multitrackpy-1.2.0.dist-info/licenses/LICENSE
bbo_multitrackpy-1.2.0.dist-info/RECORD
