Metadata-Version: 2.4
Name: bbo-multitrackpy
Version: 1.2.0
Summary: Detect head positions from MTT files
Project-URL: Homepage, https://github.com/bbo-lab/multitrackpy
Author-email: "BBO-lab @ caesar" <kay-michael.voit@mpinb.mpg.de>
License-Expression: LGPL-3.0-or-later
License-File: LICENSE
Classifier: License :: OSI Approved :: GNU Lesser General Public License v2 or later (LGPLv2+)
Classifier: Programming Language :: Python :: 3.10
Requires-Dist: bbo-bbo
Requires-Dist: bbo-calibcamlib
Requires-Dist: bbo-ccvtools
Requires-Dist: bbo-multitrackpy
Requires-Dist: construct
Requires-Dist: matplotlib
